olangfuse/__init__.py
olangfuse/open_langfuse.py
olangfuse/utils.py
olangfuse/version.py
olangfuse/components/__init__.py
olangfuse/components/open_clients.py
olangfuse/components/open_traces.py
olangfuse-0.1.2.dist-info/LICENSE
olangfuse-0.1.2.dist-info/METADATA
olangfuse-0.1.2.dist-info/WHEEL
olangfuse-0.1.2.dist-info/top_level.txt
olangfuse-0.1.2.dist-info/RECORD
