Metadata-Version: 2.1
Name: olangfuse
Version: 0.1.2
Summary: A wrapper for Langfuse to manage Trace with full CRUD operations.
Home-page: 
Author: Trinh Do Duy Hung
Author-email: trinhhungsss492@gmail.com
License: MIT
License-File: LICENSE
Requires-Dist: langfuse
Requires-Dist: pycookiecheat
Requires-Dist: requests
